elli/__init__.py
elli-1.0.2.dist-info/METADATA
elli-1.0.2.dist-info/WHEEL
elli-1.0.2.dist-info/licenses/LICENSE
elli-1.0.2.dist-info/RECORD
