Metadata-Version: 2.1
Name: elli
Version: 1.0.2
Summary: Elli operates on intel hex files, raw binary data, or python dictionaries
Project-URL: Homepage, https://github.com/busserull/elli
Project-URL: Issues, https://github.com/busserull/elli/issues
Author: Kolbjørn Austreng
License-File: LICENSE
Classifier: License :: OSI Approved :: GNU General Public License v3 or later (GPLv3+)
Classifier: Operating System :: OS Independent
Classifier: Programming Language :: Python :: 3
Requires-Python: >=3.7
